odoo/addons/account_invoice_export/README.rst
odoo/addons/account_invoice_export/__init__.py
odoo/addons/account_invoice_export/__manifest__.py
odoo/addons/account_invoice_export/data/mail_activity_type.xml
odoo/addons/account_invoice_export/data/queue_job_data.xml
odoo/addons/account_invoice_export/i18n/account_invoice_export.pot
odoo/addons/account_invoice_export/i18n/es.po
odoo/addons/account_invoice_export/models/__init__.py
odoo/addons/account_invoice_export/models/account_move.py
odoo/addons/account_invoice_export/models/transmit_method.py
odoo/addons/account_invoice_export/readme/CONTRIBUTORS.rst
odoo/addons/account_invoice_export/readme/CREDITS.rst
odoo/addons/account_invoice_export/readme/DESCRIPTION.rst
odoo/addons/account_invoice_export/static/description/icon.png
odoo/addons/account_invoice_export/static/description/index.html
odoo/addons/account_invoice_export/tests/__init__.py
odoo/addons/account_invoice_export/tests/test_export_invoice.py
odoo/addons/account_invoice_export/views/account_move.xml
odoo/addons/account_invoice_export/views/message_template.xml
odoo/addons/account_invoice_export/views/transmit_method.xml
odoo14_addon_account_invoice_export-14.0.1.2.5.dist-info/METADATA
odoo14_addon_account_invoice_export-14.0.1.2.5.dist-info/WHEEL
odoo14_addon_account_invoice_export-14.0.1.2.5.dist-info/top_level.txt
odoo14_addon_account_invoice_export-14.0.1.2.5.dist-info/RECORD
